trongitpy/__init__.py
trongitpy/main.py
trongitpy-0.0.1.dist-info/licenses/LICENSE.txt
trongitpy-0.0.1.dist-info/METADATA
trongitpy-0.0.1.dist-info/WHEEL
trongitpy-0.0.1.dist-info/top_level.txt
trongitpy-0.0.1.dist-info/RECORD
